Workbook

Sheet Portfolio Allocation
B2: Hypothetical Investment Portfolio — Rs 1,00,000
B3: CodeAlpha Finance & Investment Analysis Internship — Task 3 | E3: USD/INR Rate: | F3: 88.5
B4: Data as of: October 13, 2026 | USD/INR assumed: 88.50
B6: Asset Class | C6: Asset | D6: Price (Rs) | E6: Allocation (%) | F6: Amount (Rs) | G6: Units (approx.)
B7: Stocks | C7: Microsoft Corporation (MSFT) | D7: 46055.4 | E7: 0.15 | F7: =100000*E7 -> 15000 | G7: =F7/D7 -> 0.32569471
B8: Stocks | C8: Apple Inc. (AAPL) | D8: 29531.57 | E8: 0.13 | F8: =100000*E8 -> 13000 | G8: =F8/D8 -> 0.44020687
B9: Stocks | C9: NVIDIA Corporation (NVDA) | D9: 20397.48 | E9: 0.12 | F9: =100000*E9 -> 12000 | G9: =F9/D9 -> 0.58830797
B10: ETFs | C10: Nippon India ETF Nifty 50 BeES (NIFTYBEES) | D10: 268.81 | E10: 0.15 | F10: =100000*E10 -> 15000 | G10: =F10/D10 -> 55.801495
B11: ETFs | C11: Motilal Oswal Nasdaq 100 ETF (MON100) | D11: 332.8 | E11: 0.12 | F11: =100000*E11 -> 12000 | G11: =F11/D11 -> 36.057692
B12: ETFs | C12: Nippon India ETF Gold BeES (GOLDBEES) | D12: 125.84 | E12: 0.08 | F12: =100000*E12 -> 8000 | G12: =F12/D12 -> 63.572791
B13: Crypto | C13: Bitcoin (BTC) | D13: =79700*$F$3 -> 7053450 | E13: 0.1125 | F13: =100000*E13 -> 11250 | G13: =F13/D13 -> 0.0015949642
B14: Crypto | C14: Ethereum (ETH) | D14: =2500*$F$3 -> 221250 | E14: 0.075 | F14: =100000*E14 -> 7500 | G14: =F14/D14 -> 0.033898305
B15: Crypto | C15: Solana (SOL) | D15: =104*$F$3 -> 9204 | E15: 0.0625 | F15: =100000*E15 -> 6250 | G15: =F15/D15 -> 0.67905259
B16: TOTAL | E16: =SUM(E7:E15) -> 1 | F16: =SUM(F7:F15) -> 100000
B18: Note: Crypto amounts are converted to INR using the USD/INR rate in cell F3 (blue, editable).

Sheet Category Summary
B2: Allocation by Asset Class
B4: Asset Class | C4: Allocation (%) | D4: Amount (Rs) | E4: Rationale
B5: Stocks | C5: ='Portfolio Allocation'!E7+'Portfolio Allocation'!E8+'Portfolio Allocation'!E9 -> 0.4 | D5: ='Portfolio Allocation'!F7+'Portfolio Allocation'!F8+'Portfolio Allocation'!F9 -> 40000 | E5: Direct equity exposure to high-conviction Indian large-caps across autos, pharma and telecom for capital growth and sector diversification.
B6: ETFs | C6: ='Portfolio Allocation'!E10+'Portfolio Allocation'!E11+'Portfolio Allocation'!E12 -> 0.35 | D6: ='Portfolio Allocation'!F10+'Portfolio Allocation'!F11+'Portfolio Allocation'!F12 -> 35000 | E6: Low-cost, diversified core: broad Indian market (Nifty 50), US tech exposure (Nasdaq 100), and a gold hedge for stability.
B7: Crypto | C7: ='Portfolio Allocation'!E13+'Portfolio Allocation'!E14+'Portfolio Allocation'!E15 -> 0.25 | D7: ='Portfolio Allocation'!F13+'Portfolio Allocation'!F14+'Portfolio Allocation'!F15 -> 25000 | E7: Small, high-conviction allocation to digital assets (BTC/ETH/SOL) for asymmetric growth potential, sized to limit downside.
B8: TOTAL | C8: =C5+C6+C7 -> 1 | D8: =D5+D6+D7 -> 100000

Sheet Rationale & Notes
B2: Investment Rationale
B4: Why this mix (40% Stocks / 35% ETFs / 25% Crypto)
B5: The allocation leads with direct equities (40%) to capture high-conviction growth from industry-leading tech mega-caps, uses ETFs (35%) as a low-cost, broad-market stabilizing core, and caps cryptocurrency at 25% to manage downside exposure given its higher volatility profile (see Task 2 analysis: 41-80% realized volatility vs. single-digit-to-teens for equities/ETFs).
B7: Stock selection logic
B8: Microsoft, Apple, and NVIDIA represent three distinct, non-overlapping pillars of the global technology economy (enterprise cloud/software, consumer hardware/services, and AI semiconductor infrastructure). Each possesses strong individual growth drivers ranging from Azure AI monetization and record-breaking services revenue to dominant data center compute demand.
B10: ETF selection logic
B11: Nifty 50 BeES gives broad, low-cost Indian large-cap exposure (0.03% expense ratio). Nasdaq 100 ETF adds international/US tech diversification, reducing dependence on the Indian market alone. Gold BeES acts as a defensive hedge, historically less correlated with equities and crypto.
B13: Crypto selection logic
B14: BTC/ETH/SOL are weighted 45/30/25 within the crypto sleeve (per Task 2), anchoring the high-beta portfolio in Bitcoin’s deeper institutional liquidity while maintaining strategic upside exposure to Ethereum’s smart-contract dominance and Solana’s high-throughput Layer-1 ecosystem.
B16: Risk management
B17: No single holding exceeds 15% of the total portfolio. The ETF and defensive asset sleeve provides an essential counterweight, dampening drawdowns from the higher-volatility stock and crypto holdings.
B18: Disclaimer: This is a hypothetical portfolio prepared for educational purposes as part of the CodeAlpha internship and does not constitute investment advice. Verify current prices before making any real investment decisions.
